otocp/__init__.py
otocp/todo.py
otocp-1.0.1.dist-info/METADATA
otocp-1.0.1.dist-info/WHEEL
otocp-1.0.1.dist-info/entry_points.txt
otocp-1.0.1.dist-info/top_level.txt
otocp-1.0.1.dist-info/RECORD
