Metadata-Version: 2.4
Name: otocp
Version: 1.0.1
Summary: A MCP server written in python to add, list, complete and delete tasks in Obsidian.
Requires-Python: >=3.13
Requires-Dist: mcp[cli]>=1.11.0
